README.md
ppb_timing.py
setup.py
ppb_timing.egg-info/PKG-INFO
ppb_timing.egg-info/SOURCES.txt
ppb_timing.egg-info/dependency_links.txt
ppb_timing.egg-info/requires.txt
ppb_timing.egg-info/top_level.txt