Metadata-Version: 2.1
Name: ppb-timing
Version: 0.1.1
Summary: A timing system for PursuedPyBear games.
Home-page: https://github.com/ironfroggy/ppb_timing
Author: Calvin Spealman
Author-email: ironfroggy@gmail.com
License: UNKNOWN
Platform: UNKNOWN
Classifier: Programming Language :: Python :: 3
Classifier: Topic :: Games/Entertainment
Provides-Extra: dev
